MANIFEST.in
Makefile
requirements.txt
setup.py
wsgi.py
_site/.htaccess
_site/apple-touch-icon-114x114-precomposed.png
_site/apple-touch-icon-144x144-precomposed.png
_site/apple-touch-icon-57x57-precomposed.png
_site/apple-touch-icon-72x72-precomposed.png
_site/apple-touch-icon-precomposed.png
_site/apple-touch-icon.png
_site/crossdomain.xml
_site/favicon.ico
_site/humans.txt
_site/robots.txt
_site/maintenance/index.html
bin/manage.py
server/apache/production.conf
server/nginx/development.conf
server/nginx/local.conf
server/supervisor/development.ini
server/supervisor/local.ini
server/uwsgi/development.ini
server/uwsgi/local.ini
varify/__init__.py
varify/backends.py
varify/context_processors.py
varify/formatters.py
varify/models.py
varify/views.py
varify.egg-info/PKG-INFO
varify.egg-info/SOURCES.txt
varify.egg-info/dependency_links.txt
varify.egg-info/requires.txt
varify.egg-info/top_level.txt
varify/accounts/__init__.py
varify/accounts/context_processors.py
varify/accounts/urls.py
varify/accounts/utils.py
varify/accounts/views.py
varify/api/__init__.py
varify/api/models.py
varify/api/templates.py
varify/api/urls.py
varify/assessments/__init__.py
varify/assessments/admin.py
varify/assessments/formatters.py
varify/assessments/forms.py
varify/assessments/models.py
varify/assessments/resources.py
varify/conf/__init__.py
varify/conf/global_settings.py
varify/conf/routers.py
varify/conf/search_sites.py
varify/conf/settings.py
varify/conf/urls.py
varify/fixtures/0002_avocado_metadata.json
varify/fixtures/initial_data.json
varify/genes/__init__.py
varify/genes/admin.py
varify/genes/formatters.py
varify/genes/forms.py
varify/genes/models.py
varify/genes/resources.py
varify/genes/urls.py
varify/genes/views.py
varify/genes/templates/genes/geneset-form.html
varify/genome/__init__.py
varify/genome/admin.py
varify/genome/models.py
varify/migrations/0001_initial.py
varify/migrations/0002_avocado_metadata_migration.py
varify/migrations/0003_fix_sequence_problems.py
varify/migrations/0004_remove_sample_as_queryable.py
varify/migrations/__init__.py
varify/phenotypes/__init__.py
varify/phenotypes/models.py
