Metadata-Version: 1.1
Name: varify
Version: 0.8.0
Summary: Clinical DNA Sequencing Analysis and Data Discovery
Home-page: http://github.com/cbmi/varify
Author: Byron Ruth
Author-email: b@devel.io
License: bsd
Keywords: vcf dna clinical sequence harvest genome
Platform: UNKNOWN
Classifier: Development Status :: 5 - Production/Stable
Classifier: License :: OSI Approved :: BSD License
Classifier: Programming Language :: Python :: 2.6
Classifier: Programming Language :: Python :: 2.7
Classifier: Framework :: Django
Classifier: Topic :: Internet :: WWW/HTTP
Classifier: Intended Audience :: Developers
Classifier: Intended Audience :: Science/Research
Classifier: Intended Audience :: Healthcare Industry
Classifier: Intended Audience :: Information Technology
